LICENSE
MANIFEST.in
README.md
pyproject.toml
setup.cfg
setup.py
anzo_jupyter/__init__.py
anzo_jupyter/anzo_jupyter.py
anzo_jupyter/anzo_jupyter_util.py
anzo_jupyter/anzo_magics.py
anzo_jupyter/anzo_managers.py
anzo_jupyter/anzo_queries.py
anzo_jupyter/arrow_flight_magics.py
anzo_jupyter/graph_vis.py
anzo_jupyter/secrets_manager.py
anzo_jupyter.egg-info/PKG-INFO
anzo_jupyter.egg-info/SOURCES.txt
anzo_jupyter.egg-info/dependency_links.txt
anzo_jupyter.egg-info/not-zip-safe
anzo_jupyter.egg-info/requires.txt
anzo_jupyter.egg-info/top_level.txt
docs/Makefile
docs/anzo_jupyter.rst
docs/conf.py
docs/contributing.rst
docs/history.rst
docs/index.rst
docs/installation.rst
docs/make.bat
docs/modules.rst
docs/readme.rst
docs/usage.rst
tests/__init__.py
tests/sample_flight_server.py
tests/test_basic.py
tests/test_common.py
tests/test_flight_magics.py
tests/test_graph_vis.py
tests/test_assets/export_flds/flds.trig
tests/test_assets/export_flds/onts/.ontsdir
tests/test_assets/export_flds/onts/PyAnzo_Dictionary_-_PyAnzo_Datasource_-_Auto.trig
tests/test_assets/pyanzo_test_dataset/.lsdir
tests/test_assets/pyanzo_test_dataset/flds.trig
tests/test_assets/pyanzo_test_dataset/onts/.ontsdir
tests/test_assets/pyanzo_test_dataset/onts/PyAnzo_Dictionary_-_PyAnzo_Datasource_-_Auto.trig
tests/test_assets/pyanzo_test_dataset/rdf.ttl.gz/Loaddata_Person_734ff.ttl.gz/20200502131201.ttl.gz/.jobMetadata
tests/test_assets/pyanzo_test_dataset/rdf.ttl.gz/Loaddata_Person_734ff.ttl.gz/20200502131201.ttl.gz/.lsdir
tests/test_assets/pyanzo_test_dataset/rdf.ttl.gz/Loaddata_Person_734ff.ttl.gz/20200502131201.ttl.gz/part-00000.gz.ttl.gz
tests/test_assets/trig/PyAnzo_AZG.trig
tests/test_assets/trig/PyAnzo_Graphmart_export.trig
tests/test_assets/trig/PyAnzo_Graphmart_graph.trig
tests/test_assets/trig/PyAnzo_Graphmart_registry.trig