Metadata-Version: 2.1
Name: anzo-jupyter
Version: 2.2.5
Summary: Jupyter
Home-page: 
Author: Tommy Fang, Adam Sachs, Alex Ledger
Author-email: "Tommy Fang, Adam Sachs, Alex Ledger" <info@cambridgesemantics.com>
Project-URL: Support, https://stackoverflow.com/questions/tagged/anzograph
Keywords: anzo_jupyter
Classifier: Intended Audience :: Developers
Classifier: Natural Language :: English
Classifier: Programming Language :: Python :: 3
Classifier: Programming Language :: Python :: 3.5
Classifier: Programming Language :: Python :: 3.6
Classifier: Programming Language :: Python :: 3.7
Classifier: Programming Language :: Python :: 3.8
Classifier: Programming Language :: Python :: 3.9
Classifier: Programming Language :: Python :: 3.10
Requires-Python: >=3.5
License-File: LICENSE
